DLearn2/__init__.py
dlearn2-0.1.6.dist-info/METADATA
dlearn2-0.1.6.dist-info/WHEEL
dlearn2-0.1.6.dist-info/top_level.txt
dlearn2-0.1.6.dist-info/RECORD
