Metadata-Version: 2.4
Name: DLearn2
Version: 0.1.6
Summary: My DLearn2 library
Author: Samosax
